exrex_variant_generator/__init__.py
exrex_variant_generator-2025.9.142053.dist-info/licenses/LICENSE
exrex_variant_generator-2025.9.142053.dist-info/METADATA
exrex_variant_generator-2025.9.142053.dist-info/WHEEL
exrex_variant_generator-2025.9.142053.dist-info/top_level.txt
exrex_variant_generator-2025.9.142053.dist-info/RECORD
