Metadata-Version: 2.4
Name: exrex_variant_generator
Version: 2025.9.142053
Author-email: Eugene Evstafev <hi@eugene.plus>
License: MIT License
Project-URL: Repository, https://pypi.org/project/exrex_variant_generator/
Requires-Python: >=3.9
License-File: LICENSE
Requires-Dist: exrex
Dynamic: license-file
